rism/conv/__init__.py
rism/conv/_version.py
rism/conv/amber.py
rism/conv/base.py
rism/conv/rism.py
rism_conv-0.1.1.dist-info/licenses/LICENSE
rism_conv-0.1.1.dist-info/METADATA
rism_conv-0.1.1.dist-info/WHEEL
rism_conv-0.1.1.dist-info/entry_points.txt
rism_conv-0.1.1.dist-info/top_level.txt
rism_conv-0.1.1.dist-info/RECORD
