Metadata-Version: 2.4
Name: rism-conv
Version: 0.1.1
Summary: Converters into RISM molecule format .rtxt
Author: Egor Sobolev
Maintainer: Egor Sobolev
License: BSD-3-Clause
Project-URL: Homepage, https://github.com/egorsobolev/rism-conv
Classifier: Development Status :: 4 - Beta
Classifier: Environment :: Console
Classifier: Intended Audience :: Science/Research
Classifier: License :: OSI Approved :: BSD License
Classifier: Operating System :: POSIX :: Linux
Classifier: Programming Language :: Python :: 3
Classifier: Topic :: Scientific/Engineering :: Physics
Classifier: Topic :: Utilities
Requires-Python: >=3.9
License-File: LICENSE
Requires-Dist: parmed
Dynamic: license-file
